Metadata-Version: 2.1
Name: bacpage
Version: 2024.3.8
Summary: An easy-to-use pipeline for the assembly and analysis of bacterial genomes
Author-email: Nate Matteson <nmatteson@bwh.harvard.edu>, watronfire <snowboardman007@gmail.com>
License: GNU GENERAL PUBLIC LICENSE
Project-URL: Homepage, https://github.com/CholGen/bacpage
Project-URL: Repository, https://github.com/CholGen/bacpage.git
Keywords: bacteria,NGS,snakemake,phylogenetics
Classifier: Development Status :: 4 - Beta
Classifier: Intended Audience :: Science/Research
Classifier: Programming Language :: Python :: 3
Classifier: Natural Language :: English
Classifier: Topic :: Scientific/Engineering :: Bio-Informatics
Requires-Python: <3.12,>=3.9
License-File: LICENSE
Requires-Dist: biopython
Requires-Dist: pandas
Requires-Dist: pyyaml
Requires-Dist: setuptools
Requires-Dist: jinja2
